google_search_resource-0.0.2.dist-info/licenses/LICENSE
gsr/__init__.py
gsr/browser.py
gsr/captcha.py
gsr/cli.py
gsr/enums.py
gsr/models.py
gsr/searcher.py
gsr/session.py
google_search_resource-0.0.2.dist-info/METADATA
google_search_resource-0.0.2.dist-info/WHEEL
google_search_resource-0.0.2.dist-info/entry_points.txt
google_search_resource-0.0.2.dist-info/top_level.txt
google_search_resource-0.0.2.dist-info/RECORD
