Metadata-Version: 2.4
Name: google-search-resource
Version: 0.0.2
Summary: A tool for researching and analyzing Google search page behavior and structure
Author-email: Yaacov Zamir <kobi.zamir@gmail.com>
Maintainer-email: Yaacov Zamir <kobi.zamir@gmail.com>
License: MIT
Project-URL: Homepage, https://github.com/yaacov/gsr
Project-URL: Documentation, https://github.com/yaacov/gsr#readme
Project-URL: Repository, https://github.com/yaacov/gsr
Project-URL: Issues, https://github.com/yaacov/gsr/issues
Keywords: google,search,research,web-scraping,playwright,captcha-detection,browser-automation,analysis
Classifier: Development Status :: 4 - Beta
Classifier: Intended Audience :: Developers
Classifier: Intended Audience :: Education
Classifier: Intended Audience :: Science/Research
Classifier: License :: OSI Approved :: MIT License
Classifier: Operating System :: OS Independent
Classifier: Programming Language :: Python :: 3
Classifier: Programming Language :: Python :: 3.8
Classifier: Programming Language :: Python :: 3.9
Classifier: Programming Language :: Python :: 3.10
Classifier: Programming Language :: Python :: 3.11
Classifier: Programming Language :: Python :: 3.12
Classifier: Topic :: Internet :: WWW/HTTP :: Browsers
Classifier: Topic :: Internet :: WWW/HTTP :: Dynamic Content
Classifier: Topic :: Scientific/Engineering :: Information Analysis
Classifier: Topic :: Software Development :: Libraries :: Python Modules
Requires-Python: >=3.8
License-File: LICENSE
Requires-Dist: playwright>=1.40.0
Provides-Extra: yaml
Requires-Dist: pyyaml>=6.0; extra == "yaml"
Provides-Extra: dev
Requires-Dist: black>=23.0.0; extra == "dev"
Requires-Dist: pylint>=2.17.0; extra == "dev"
Requires-Dist: pytest>=7.4.0; extra == "dev"
Requires-Dist: pyyaml>=6.0; extra == "dev"
Dynamic: license-file
